{
  "@context": "aku-v2",
  "@type": "concept",
  "@id": "micro-040-price-discrimination",
  "metadata": {
    "version": "2.0.0",
    "created": "2026-01-09T11:18:01.000Z",
    "modified": "2026-01-09T11:18:01.000Z",
    "contributors": [
      "aku-generator"
    ],
    "confidence": 0.85,
    "status": "draft"
  },
  "classification": {
    "domain_path": "economics/microeconomics",
    "type": "concept",
    "difficulty": "intermediate",
    "importance": "foundational"
  },
  "content": {
    "title": "Price Discrimination",
    "definition": "Different prices for same good",
    "key_points": [
      "Core concept of Price Discrimination"
    ],
    "examples": [
      "Example of Price Discrimination"
    ]
  },
  "relationships": {
    "prerequisites": [],
    "related_concepts": [],
    "applications": []
  }
}