{
  "@context": "aku-v2",
  "@type": "concept",
  "@id": "uro-023-urge-incontinence",
  "metadata": {
    "version": "2.0.0",
    "created": "2026-01-09T11:14:44.000Z",
    "modified": "2026-01-09T11:14:44.000Z",
    "contributors": [
      "aku-generator"
    ],
    "confidence": 0.85,
    "status": "draft"
  },
  "classification": {
    "domain_path": "health-sciences/medicine/urology",
    "type": "concept",
    "difficulty": "intermediate",
    "importance": "foundational"
  },
  "content": {
    "title": "Urge Incontinence",
    "definition": "Detrusor overactivity",
    "key_points": [
      "Core concept of Urge Incontinence"
    ],
    "clinical_pearls": [
      "Important consideration for Urge Incontinence"
    ]
  },
  "relationships": {
    "prerequisites": [],
    "related_concepts": [],
    "applications": []
  }
}