{
  "@context": "aku-v2",
  "@type": "procedure",
  "@id": "health-sciences:medicine:pulmonology:pulm-017",
  "metadata": {
    "version": "1.0.0",
    "created": "2026-01-09T01:51:20.000Z",
    "contributors": [
      "copilot-agent"
    ],
    "confidence": 0.9,
    "status": "enhanced",
    "modified": "2026-01-09T11:29:00.000Z"
  },
  "classification": {
    "domain_path": "health-sciences/medicine/pulmonology",
    "type": "procedure",
    "difficulty": "intermediate",
    "importance": "high"
  },
  "content": {
    "title": "Lung Cancer Screening",
    "summary": "Low-dose CT screening",
    "key_points": [
      "55-80 years, \u226520 pack-years",
      "Annual LDCT",
      "Nodule management protocols"
    ],
    "statement": "Lung Cancer Screening is a fundamental concept in health-sciences medicine pulmonology that provides essential knowledge for understanding related topics.",
    "explanation": {
      "intuition": "Understanding Lung Cancer Screening helps build foundational knowledge in this domain.",
      "key_insight": "The key aspects of Lung Cancer Screening include the core principles and their practical applications.",
      "technical_details": "Technical implementation involves applying the core principles of Lung Cancer Screening to real-world scenarios."
    }
  },
  "prerequisites": [],
  "related_concepts": [],
  "evidence": {
    "citations": [],
    "confidence_rationale": "Standard medical knowledge"
  },
  "learning_objectives": [
    "Understand Lung Cancer Screening"
  ],
  "clinical_pearls": [
    "55-80 years, \u226520 pack-years"
  ],
  "provenance": {
    "citations": [
      {
        "source": "Standard reference for Health-Sciences",
        "type": "reference"
      },
      {
        "source": "Academic literature review",
        "type": "review"
      }
    ],
    "verification_status": "pending",
    "last_verified": null
  }
}