{
  "@context": [
    "file://domain/_contexts/base.jsonld",
    "file://domain/_contexts/science.jsonld"
  ],
  "@type": [
    "EducationalResource",
    "ScientificConcept"
  ],
  "@id": "aku-particle-physics-002-electroweak-scale",
  "metadata": {
    "version": "1.0.0",
    "created": "2025-12-29T22:16:00.000Z",
    "contributors": [
      "physics-knowledge-base",
      "particle-physics-expert"
    ],
    "confidence": 0.96,
    "status": "enhanced",
    "last_updated": "2025-12-29T22:16:00.000Z",
    "modified": "2026-01-09T11:29:00.000Z"
  },
  "classification": {
    "domain_path": "natural-sciences/physics/particle-physics",
    "type": "definition",
    "difficulty": "intermediate",
    "importance": "foundational",
    "aku_id": "pp-002",
    "keywords": [
      "electroweak scale",
      "Higgs field",
      "vacuum expectation value",
      "weak force",
      "W boson",
      "Z boson"
    ],
    "isNativeDomain": true
  },
  "content": {
    "statement": "aku-particle-physics-002-electroweak-scale is a fundamental concept in Natural-Sciences Physics Particle-Physics that provides essential knowledge for understanding related topics and clinical/practical applications.",
    "explanation": {
      "intuition": "Understanding aku-particle-physics-002-electroweak-scale helps build foundational knowledge. The concept connects to broader principles in the field.",
      "key_insight": "The key aspects of aku-particle-physics-002-electroweak-scale include core principles, common applications, and integration with related concepts.",
      "technical_details": "Technical details involve specific mechanisms, measurements, and evidence-based applications of aku-particle-physics-002-electroweak-scale."
    },
    "values": {
      "electroweak_vev": {
        "value": 246.22,
        "unit": "GeV",
        "uncertainty": 0.01
      },
      "w_boson_mass": {
        "value": 80.377,
        "unit": "GeV",
        "uncertainty": 0.012
      },
      "z_boson_mass": {
        "value": 91.1876,
        "unit": "GeV",
        "uncertainty": 0.0021
      },
      "higgs_mass": {
        "value": 125.25,
        "unit": "GeV",
        "uncertainty": 0.17
      }
    }
  },
  "relationships": {
    "prerequisites": [],
    "related_concepts": [
      {
        "id": "aku:particle-physics:001-hierarchy-problem",
        "relationship": "contextualizes",
        "description": "Hierarchy between electroweak and Planck scales"
      },
      {
        "id": "aku:planck-units:c03-energy-scales-physics",
        "relationship": "part_of_hierarchy",
        "description": "Position in energy scale ladder"
      }
    ],
    "cross_domain_links": [
      {
        "domain": "planck-units",
        "concept": "planck_energy",
        "relationship": "compared_to"
      }
    ]
  },
  "provenance": {
    "citations": [
      {
        "source": "Reference for aku-particle-physics-002-electroweak-scale",
        "type": "reference"
      },
      {
        "source": "Academic source",
        "type": "review"
      }
    ],
    "verification_status": "pending",
    "last_verified": null
  }
}