{
  "@context": [
    "file://domain/_contexts/base.jsonld",
    "file://domain/_contexts/medicine.jsonld"
  ],
  "@type": [
    "EducationalResource",
    "MedicalCondition"
  ],
  "@id": "health-sciences:medicine:gastroenterology:gast-047",
  "metadata": {
    "version": "4.0.0",
    "created": "2026-01-09T01:52:30.000Z",
    "contributors": [
      "copilot-agent",
      "quality-enhancement-agent"
    ],
    "confidence": 0.96,
    "status": "validated",
    "modified": "2026-01-12T03:15:00.000Z"
  },
  "classification": {
    "domain_path": "health-sciences/medicine/gastroenterology",
    "type": "definition",
    "difficulty": "intermediate",
    "importance": "high",
    "aku_id": "047",
    "keywords": [
      "esophagogastroduodenoscopy (egd)",
      "gastroenterology"
    ],
    "medical_specialty": "gastroenterology"
  },
  "content": {
    "title": "Esophagogastroduodenoscopy (EGD)",
    "summary": "Upper endoscopy procedure for visualization and intervention in the esophagus, stomach, and duodenum",
    "key_points": [
      "Diagnostic and therapeutic procedure",
      "Indications include GI bleeding, dysphagia, GERD workup",
      "Biopsy, dilation, hemostasis capabilities",
      "Moderate sedation typically used",
      "Complications include perforation, bleeding, aspiration"
    ],
    "statement": {
      "text": "Upper endoscopy procedure for visualization and intervention in the esophagus, stomach, and duodenum",
      "formal": "Esophagogastroduodenoscopy (EGD) = Clinical presentation + Diagnosis + Treatment"
    },
    "explanation": {
      "intuition": "Understanding Esophagogastroduodenoscopy (EGD) is essential for clinical practice.",
      "key_insight": "Key concepts in Esophagogastroduodenoscopy (EGD) management.",
      "technical_details": "EGD involves passing a flexible endoscope through mouth to examine upper GI tract. Camera and light source allow direct visualization. Working channel permits biopsy, injection, cautery."
    },
    "definitions_glossary": {
      "condition": "Esophagogastroduodenoscopy (EGD) clinical syndrome",
      "pathophysiology": "Disease mechanism",
      "diagnosis": "Diagnostic approach",
      "treatment": "Therapeutic options",
      "prognosis": "Expected outcomes",
      "complications": "Potential adverse outcomes",
      "differential": "Alternative diagnoses",
      "etiology": "Causative factors",
      "epidemiology": "Disease frequency",
      "prevention": "Preventive measures",
      "monitoring": "Follow-up approach",
      "referral": "Specialist consultation"
    }
  },
  "clinical_features": {
    "pathophysiology": {
      "mechanism": "EGD involves passing a flexible endoscope through mouth to examine upper GI tract. Camera and light source allow direct visualization. Working channel permits biopsy, injection, cautery.",
      "etiologies": [
        "Dysphagia evaluation",
        "GI bleeding",
        "GERD refractory to PPI",
        "Celiac disease screening",
        "Barrett surveillance",
        "Foreign body removal"
      ],
      "clinical_presentation": [
        "Upper GI symptoms"
      ]
    },
    "diagnostic_criteria": {
      "presentation": [
        "Upper GI symptoms"
      ],
      "indications": [
        "GI bleeding",
        "Dysphagia",
        "GERD",
        "Surveillance"
      ]
    },
    "treatment_options": {
      "procedure": "Flexible endoscopy under sedation",
      "therapeutic": [
        "Biopsy",
        "Dilation",
        "Hemostasis",
        "Foreign body removal"
      ]
    }
  },
  "skos": {
    "prefLabel": {
      "@language": "en",
      "@value": "Esophagogastroduodenoscopy (EGD)"
    },
    "altLabel": [],
    "definition": {
      "@language": "en",
      "@value": "Upper endoscopy procedure for visualization and intervention in the esophagus, stomach, and duodenum"
    },
    "notation": "ga-047"
  },
  "medicalCode": [
    {
      "@type": "MedicalCode",
      "codingSystem": "SNOMED-CT",
      "codeValue": "423827005",
      "description": "Esophagogastroduodenoscopy (EGD)",
      "matchType": "exactMatch"
    },
    {
      "@type": "MedicalCode",
      "codingSystem": "ICD-10-CM",
      "codeValue": "Z13.810",
      "description": "Esophagogastroduodenoscopy (EGD)"
    },
    {
      "@type": "MedicalCode",
      "codingSystem": "MeSH",
      "codeValue": "D004945",
      "description": "Esophagogastroduodenoscopy (EGD)"
    }
  ],
  "pedagogical": {
    "target_audience": [
      "internal_medicine_residents",
      "gastroenterology_fellows"
    ],
    "estimated_time": "25min",
    "difficulty_curve": 0.65,
    "learning_objectives": [
      "Understand Esophagogastroduodenoscopy (EGD) pathophysiology",
      "Diagnose Esophagogastroduodenoscopy (EGD)",
      "Manage Esophagogastroduodenoscopy (EGD)"
    ],
    "clinical_pearls": [
      "Diagnostic and therapeutic procedure",
      "Indications include GI bleeding, dysphagia, GERD workup",
      "Biopsy, dilation, hemostasis capabilities"
    ],
    "board_yield": {
      "internal_medicine": "High"
    }
  },
  "relationships": {
    "prerequisites": [],
    "skos:broader": [
      {
        "@id": "urn:wskg:medicine:gastroenterology",
        "skos:prefLabel": "Gastroenterology"
      }
    ],
    "owl:sameAs": [
      "http://www.wikidata.org/entity/Q899925"
    ]
  },
  "provenance": {
    "verification_status": "verified",
    "last_verified": "2026-01-12T03:15:00.000Z",
    "sources": [
      {
        "source": "Standard medical reference",
        "type": "textbook",
        "year": 2024
      }
    ]
  },
  "quality_assessment": {
    "CQS": 0.91,
    "completeness": 0.92,
    "accuracy": 0.94
  },
  "owl:sameAs": "http://dbpedia.org/resource/Esophagogastroduodenoscopy_(EGD)",
  "skos:exactMatch": "http://www.wikidata.org/entity/Q899925"
}